jingzhi/__init__.py
jingzhi/__main__.py
jingzhi-0.1.0.dist-info/METADATA
jingzhi-0.1.0.dist-info/WHEEL
jingzhi-0.1.0.dist-info/entry_points.txt
jingzhi-0.1.0.dist-info/licenses/LICENSE
jingzhi-0.1.0.dist-info/RECORD
