Metadata-Version: 2.1
Name: jingzhi
Version: 0.1.0
Summary: LLM
Author: wsk
License-File: LICENSE
Classifier: License :: OSI Approved :: MIT License
Classifier: Operating System :: OS Independent
Classifier: Programming Language :: Python :: 3
Requires-Python: >=3.6
